{
  "points": [
    {
      "id": "O1",
      "x": {
        "expr": "0",
        "latex": "0"
      },
      "y": {
        "expr": "0",
        "latex": "0"
      },
      "related_edges": [],
      "is_center": true,
      "is_circle_init": false,
      "level": 1
    },
    {
      "id": "A",
      "x": {
        "expr": "-1/2",
        "latex": "- \\frac{1}{2}"
      },
      "y": {
        "expr": "1/2",
        "latex": "\\frac{1}{2}"
      },
      "related_edges": [
        "L0",
        "L2",
        "L4",
        "L5",
        "Arc0"
      ],
      "is_center": false,
      "is_circle_init": false,
      "level": 1
    },
    {
      "id": "B",
      "x": {
        "expr": "1/2",
        "latex": "\\frac{1}{2}"
      },
      "y": {
        "expr": "-1/2",
        "latex": "- \\frac{1}{2}"
      },
      "related_edges": [
        "L0",
        "L1"
      ],
      "is_center": false,
      "is_circle_init": false,
      "level": 1
    },
    {
      "id": "C",
      "x": {
        "expr": "1/2",
        "latex": "\\frac{1}{2}"
      },
      "y": {
        "expr": "1/2",
        "latex": "\\frac{1}{2}"
      },
      "related_edges": [
        "L1",
        "L2"
      ],
      "is_center": false,
      "is_circle_init": false,
      "level": 1
    },
    {
      "id": "O2",
      "x": {
        "expr": "-1",
        "latex": "-1"
      },
      "y": {
        "expr": "0",
        "latex": "0"
      },
      "related_edges": [],
      "is_center": true,
      "is_circle_init": false,
      "level": 1
    },
    {
      "id": "D",
      "x": {
        "expr": "-3/2",
        "latex": "- \\frac{3}{2}"
      },
      "y": {
        "expr": "1/2",
        "latex": "\\frac{1}{2}"
      },
      "related_edges": [
        "L3",
        "L5",
        "Arc0"
      ],
      "is_center": false,
      "is_circle_init": false,
      "level": 2
    },
    {
      "id": "E",
      "x": {
        "expr": "-1/2",
        "latex": "- \\frac{1}{2}"
      },
      "y": {
        "expr": "-1/2",
        "latex": "- \\frac{1}{2}"
      },
      "related_edges": [
        "L3",
        "L4",
        "Arc0"
      ],
      "is_center": false,
      "is_circle_init": false,
      "level": 2
    },
    {
      "id": "circle_1",
      "x": {
        "expr": "-1 + sqrt(2)/2",
        "latex": "-1 + \\frac{\\sqrt{2}}{2}"
      },
      "y": {
        "expr": "0",
        "latex": "0"
      },
      "related_edges": [
        "Arc0"
      ],
      "is_center": false,
      "is_circle_init": true,
      "level": 2
    }
  ],
  "lines": [
    {
      "id": "L0",
      "type": "line",
      "start_point_id": "A",
      "end_point_id": "B",
      "level": 1,
      "is_original": true,
      "is_minimal": false,
      "length": {
        "expr": "sqrt(2)",
        "latex": "\\sqrt{2}",
        "value": 1.41421356
      }
    },
    {
      "id": "L1",
      "type": "line",
      "start_point_id": "B",
      "end_point_id": "C",
      "level": 1,
      "is_original": true,
      "is_minimal": true,
      "length": {
        "expr": "1",
        "latex": "1",
        "value": 1.0
      }
    },
    {
      "id": "L2",
      "type": "line",
      "start_point_id": "C",
      "end_point_id": "A",
      "level": 1,
      "is_original": true,
      "is_minimal": true,
      "length": {
        "expr": "1",
        "latex": "1",
        "value": 1.0
      }
    },
    {
      "id": "L3",
      "type": "line",
      "start_point_id": "D",
      "end_point_id": "E",
      "level": 2,
      "is_original": true,
      "is_minimal": false,
      "length": {
        "expr": "sqrt(2)",
        "latex": "\\sqrt{2}",
        "value": 1.41421356
      }
    },
    {
      "id": "L4",
      "type": "line",
      "start_point_id": "E",
      "end_point_id": "A",
      "level": 2,
      "is_original": true,
      "is_minimal": true,
      "length": {
        "expr": "1",
        "latex": "1",
        "value": 1.0
      }
    },
    {
      "id": "L5",
      "type": "line",
      "start_point_id": "A",
      "end_point_id": "D",
      "level": 2,
      "is_original": true,
      "is_minimal": true,
      "length": {
        "expr": "1",
        "latex": "1",
        "value": 1.0
      }
    },
    {
      "id": "L_min_1",
      "start_point_id": "A",
      "end_point_id": "O1",
      "level": 1,
      "is_original": false,
      "is_minimal": true,
      "length": {
        "expr": "sqrt(2)/2",
        "latex": "\\frac{\\sqrt{2}}{2}",
        "value": 0.70710678
      }
    },
    {
      "id": "L_min_2",
      "start_point_id": "O1",
      "end_point_id": "B",
      "level": 1,
      "is_original": false,
      "is_minimal": true,
      "length": {
        "expr": "sqrt(2)/2",
        "latex": "\\frac{\\sqrt{2}}{2}",
        "value": 0.70710678
      }
    },
    {
      "id": "L_min_3",
      "start_point_id": "D",
      "end_point_id": "O2",
      "level": 2,
      "is_original": false,
      "is_minimal": true,
      "length": {
        "expr": "sqrt(2)/2",
        "latex": "\\frac{\\sqrt{2}}{2}",
        "value": 0.70710678
      }
    },
    {
      "id": "L_min_4",
      "start_point_id": "O2",
      "end_point_id": "E",
      "level": 2,
      "is_original": false,
      "is_minimal": true,
      "length": {
        "expr": "sqrt(2)/2",
        "latex": "\\frac{\\sqrt{2}}{2}",
        "value": 0.70710678
      }
    }
  ],
  "arcs": [
    {
      "id": "Arc0",
      "type": "arc",
      "start_point_id": "circle_1",
      "end_point_id": "circle_1",
      "center_point_id": "O2",
      "radius": {
        "expr": "sqrt(2)/2",
        "latex": "\\frac{\\sqrt{2}}{2}"
      },
      "angle": {
        "expr": "2*pi",
        "latex": "2 \\pi"
      },
      "is_complete": true,
      "level": 2,
      "is_original": true,
      "is_minimal": false,
      "length": {
        "expr": "sqrt(2)*pi",
        "latex": "\\sqrt{2} \\pi",
        "value": 4.44288294
      }
    },
    {
      "id": "Arc_min_1",
      "start_point_id": "E",
      "end_point_id": "circle_1",
      "center_point_id": "O2",
      "radius": {
        "expr": "sqrt(2)/2"
      },
      "angle": {
        "expr": "pi/4"
      },
      "is_complete": false,
      "is_original": false,
      "is_minimal": true,
      "level": 2,
      "length": {
        "expr": "sqrt(2)*pi/8",
        "latex": "\\frac{\\sqrt{2} \\pi}{8}",
        "value": 0.55536037
      }
    },
    {
      "id": "Arc_min_2",
      "start_point_id": "circle_1",
      "end_point_id": "A",
      "center_point_id": "O2",
      "radius": {
        "expr": "sqrt(2)/2"
      },
      "angle": {
        "expr": "pi/4"
      },
      "is_complete": false,
      "is_original": false,
      "is_minimal": true,
      "level": 2,
      "length": {
        "expr": "sqrt(2)*pi/8",
        "latex": "\\frac{\\sqrt{2} \\pi}{8}",
        "value": 0.55536037
      }
    },
    {
      "id": "Arc_min_3",
      "start_point_id": "A",
      "end_point_id": "D",
      "center_point_id": "O2",
      "radius": {
        "expr": "sqrt(2)/2"
      },
      "angle": {
        "expr": "pi/2"
      },
      "is_complete": false,
      "is_original": false,
      "is_minimal": true,
      "level": 2,
      "length": {
        "expr": "sqrt(2)*pi/4",
        "latex": "\\frac{\\sqrt{2} \\pi}{4}",
        "value": 1.11072074
      }
    },
    {
      "id": "Arc_min_4",
      "start_point_id": "D",
      "end_point_id": "E",
      "center_point_id": "O2",
      "radius": {
        "expr": "sqrt(2)/2"
      },
      "angle": {
        "expr": "pi"
      },
      "is_complete": false,
      "is_original": false,
      "is_minimal": true,
      "level": 2,
      "length": {
        "expr": "sqrt(2)*pi/2",
        "latex": "\\frac{\\sqrt{2} \\pi}{2}",
        "value": 2.22144147
      }
    }
  ],
  "entities": [
    {
      "id": "base_right_triangle_1:1",
      "type": "special_triangle",
      "subtype": "right",
      "center_id": "O1",
      "rotate_mode": "original",
      "is_base": true,
      "vertices": [
        "A",
        "B",
        "C"
      ],
      "lines": [
        "L0",
        "L1",
        "L2"
      ],
      "leg1": {
        "expr": "1",
        "latex": "1"
      },
      "leg2": {
        "expr": "1",
        "latex": "1"
      },
      "hypotenuse": {
        "expr": "sqrt(2)",
        "latex": "\\sqrt{2}"
      },
      "perimeter": {
        "expr": "sqrt(2) + 2",
        "latex": "\\sqrt{2} + 2"
      },
      "area": {
        "expr": "1/2",
        "latex": "\\frac{1}{2}"
      }
    },
    {
      "id": "translated_right_triangle_edge2",
      "type": "special_triangle",
      "subtype": "right",
      "center_id": "O2",
      "rotate_mode": "original",
      "is_base": false,
      "vertices": [
        "D",
        "E",
        "A"
      ],
      "lines": [
        "L3",
        "L4",
        "L5"
      ],
      "leg1": {
        "expr": "1",
        "latex": "1"
      },
      "leg2": {
        "expr": "1",
        "latex": "1"
      },
      "hypotenuse": {
        "expr": "sqrt(2)",
        "latex": "\\sqrt{2}"
      },
      "perimeter": {
        "expr": "sqrt(2) + 2",
        "latex": "\\sqrt{2} + 2"
      },
      "area": {
        "expr": "1/2",
        "latex": "\\frac{1}{2}"
      }
    },
    {
      "id": "circumscribedcircle_triangle_right",
      "type": "circle",
      "center_id": "O2",
      "start_id": "circle_1",
      "end_id": "circle_1",
      "arcs": "Arc0",
      "radius": {
        "expr": "sqrt(2)/2",
        "latex": "\\frac{\\sqrt{2}}{2}"
      },
      "start_angle": {
        "expr": "0",
        "latex": "0"
      },
      "end_angle": {
        "expr": "2*pi",
        "latex": "2 \\pi"
      },
      "is_complete": true,
      "is_base": false,
      "perimeter": {
        "expr": "sqrt(2)*pi",
        "latex": "\\sqrt{2} \\pi"
      },
      "area": {
        "expr": "pi/2",
        "latex": "\\frac{\\pi}{2}"
      }
    },
    {
      "type": "shadow",
      "region_label": 5,
      "points": [
        {
          "id": "A"
        },
        {
          "id": "E"
        },
        {
          "id": "circle_1"
        }
      ],
      "lines": [
        {
          "id": "L4"
        }
      ],
      "arcs": [
        {
          "id": "Arc_min_1"
        },
        {
          "id": "Arc_min_2"
        }
      ],
      "ordered_loops": [
        {
          "ordered_points": [
            "E",
            "circle_1",
            "A",
            "E"
          ]
        }
      ],
      "validity": true,
      "perimeter": {
        "expr": "1 + sqrt(2)*pi/4",
        "latex": "1 + \\frac{\\sqrt{2} \\pi}{4}"
      },
      "area": {
        "expr": "-1/4 + pi/8",
        "latex": "- \\frac{1}{4} + \\frac{\\pi}{8}"
      }
    }
  ],
  "description": "Original graphic description: Base shape is a right triangle (hypotenuse midpoint O1) with legs 1, 1, rotate mode original Round 1: applying 'translation' rule. Translated right triangle along edge L2 by full length (new origin O2). Round 2: applying 'circum_inscribe' rule. Circumscribed circle for right triangle. Center: O2, Radius: sqrt(2)/2.\nEnhancement index: 1/5\nNumber of rounds: 0\nNo enhancement.",
  "is_base": true,
  "timeout_occurred": false,
  "completed_rounds": 0,
  "base_id": "",
  "enhance_id": "_enhance_000",
  "raw_path": "./results_n500_v4/images/raw/geometry_line_0063.png",
  "annotated_raw_path": "./results_n500_v4/images/annotated/annotated_raw_geometry_line_0063.png",
  "shaded_path": "./results_n500_v4/images/shaded/shaded_62_attempt_1_geometry_line_0063.png",
  "annotated_shaded_path": "./results_n500_v4/images/annotated/annotated_shaded_62_attempt_1_geometry_line_0063.png",
  "shadow_type": "hatch",
  "shader_enabled": true,
  "shadow_regions": 1,
  "generated_question": [
    "{\n  \"question\": \"Given that triangle ABC is a right triangle with legs AB and BC each of length 1, and O1 is the midpoint of hypotenuse AC, after translating the triangle along edge L2 (from A to D) by its full length to form a new triangle with origin O2, and constructing circumscribedcircle_triangle_right centered at O2 with radius sqrt(2)/2, find the length of arc Arc0 subtended by chord DE in circle_1.\",\n  \"difficulty_label\": 4,\n  \"question_type\": \"length\",\n  \"target_ids\": [\"Arc0\", \"circle_1\", \"O2\", \"D\", \"E\"]\n}"
  ]
}